llama_d5/__init__.py
llama_d5/config.py
llama_d5/core.py
llama_d5/llama_screenshot.py
llama_d5/llamadoc2pdf/__init__.py
llama_d5/llamadoc2pdf/__main__.py
llama_d5/llamadoc2pdf/llm_integration.py
llama_d5/llamadoc2pdf/main.py
llama_d5/llamadoc2pdf/agents/core.py
llama_d5/llamadoc2pdf/agents/visualization.py
llama_d5/llamadoc2pdf/config/__init__.py
llama_d5/llamadoc2pdf/config/advanced_settings.py
llama_d5/llamadoc2pdf/config/settings.py
llama_d5/llamadoc2pdf/core/engine.py
llama_d5/llamadoc2pdf/core/exceptions.py
llama_d5/llamadoc2pdf/core/llama_index_integration.py
llama_d5/llamadoc2pdf/core/scraper.py
llama_d5/llamadoc2pdf/processors/document.py
llama_d5/llamadoc2pdf/processors/html_renderer.py
llama_d5/llamadoc2pdf/processors/media.py
llama_d5/llamadoc2pdf/processors/webpage.py
llama_d5/llamadoc2pdf/vision/mlx_processor.py
llama_d5-0.1.0.dist-info/METADATA
llama_d5-0.1.0.dist-info/WHEEL
llama_d5-0.1.0.dist-info/entry_points.txt
llama_d5-0.1.0.dist-info/licenses/LICENSE
llama_d5-0.1.0.dist-info/RECORD
