Metadata-Version: 2.4
Name: llama-d5
Version: 0.1.0
Summary: A comprehensive document and web page conversion toolkit powered by Llama AI
Project-URL: Homepage, https://github.com/llama-ai/llama-d5
Project-URL: Bug Tracker, https://github.com/llama-ai/llama-d5/issues
Author-email: Llama D5 Team <team@llamad5.dev>
License: MIT License
License-File: LICENSE
Classifier: Development Status :: 3 - Alpha
Classifier: Intended Audience :: Developers
Classifier: License :: OSI Approved :: MIT License
Classifier: Programming Language :: Python :: 3
Classifier: Programming Language :: Python :: 3.8
Classifier: Programming Language :: Python :: 3.9
Classifier: Programming Language :: Python :: 3.10
Classifier: Programming Language :: Python :: 3.11
Classifier: Topic :: Documentation
Classifier: Topic :: Internet :: WWW/HTTP :: Browsers
Classifier: Topic :: Text Processing
Classifier: Topic :: Utilities
Requires-Python: >=3.8
Requires-Dist: aiohttp>=3.8.3
Requires-Dist: alembic>=1.12.0
Requires-Dist: anticaptchaofficial>=1.0.54
Requires-Dist: beautifulsoup4>=4.12.2
Requires-Dist: cloudscraper>=1.2.60
Requires-Dist: docx2pdf>=0.1.8
Requires-Dist: fake-useragent>=1.1.1
Requires-Dist: fastapi>=0.104.0
Requires-Dist: img2pdf>=0.5.0
Requires-Dist: langchain>=0.0.267
Requires-Dist: llama-index-tools-playwright>=0.1.0
Requires-Dist: llm-cmd>=0.1.0
Requires-Dist: llm-mlx>=0.2.0
Requires-Dist: markdown2>=2.4.6
Requires-Dist: markdown>=3.5.1
Requires-Dist: mlx>=0.8.0
Requires-Dist: networkx>=3.2
Requires-Dist: numpy>=1.24.2
Requires-Dist: openai>=1.0.0
Requires-Dist: opencv-python-headless>=4.7.0.68
Requires-Dist: pdfkit>=1.0.0
Requires-Dist: pikepdf>=6.2.5
Requires-Dist: pillow>=10.0.0
Requires-Dist: playwright-pdf>=0.1.3
Requires-Dist: playwright-stealth>=1.0.7
Requires-Dist: playwright>=1.40.0
Requires-Dist: pydantic-settings>=2.0.3
Requires-Dist: pydantic>=2.4.2
Requires-Dist: pypdf2>=2.12.1
Requires-Dist: pypdf>=4.0.0
Requires-Dist: python-dotenv>=1.0.0
Requires-Dist: reportlab>=4.0.4
Requires-Dist: requests-html>=0.10.0
Requires-Dist: requests>=2.31.0
Requires-Dist: rich>=13.0.0
Requires-Dist: selenium-stealth>=1.0.6
Requires-Dist: selenium>=4.8.0
Requires-Dist: setuptools>=68.0.0
Requires-Dist: shot-scraper>=0.9.0
Requires-Dist: sqlalchemy>=2.0.23
Requires-Dist: tf-playwright-stealth>=0.1.0
Requires-Dist: tqdm>=4.66.1
Requires-Dist: typer>=0.9.0
Requires-Dist: undetected-chromedriver>=3.2.0
Requires-Dist: uvicorn>=0.23.2
Requires-Dist: weasyprint>=60.1
Provides-Extra: all
Requires-Dist: black>=23.10.1; extra == 'all'
Requires-Dist: flake8>=6.1.0; extra == 'all'
Requires-Dist: isort>=5.12.0; extra == 'all'
Requires-Dist: mypy>=1.6.1; extra == 'all'
Requires-Dist: pre-commit>=3.5.0; extra == 'all'
Requires-Dist: pytest-cov>=4.1.0; extra == 'all'
Requires-Dist: pytest-mock>=3.12.0; extra == 'all'
Requires-Dist: pytest-playwright-asyncio>=0.7.0; extra == 'all'
Requires-Dist: pytest-playwright>=0.7.0; extra == 'all'
Requires-Dist: pytest-sugar>=0.9.7; extra == 'all'
Requires-Dist: pytest>=7.4.3; extra == 'all'
Requires-Dist: ruff>=0.0.260; extra == 'all'
Requires-Dist: tox>=4.11.3; extra == 'all'
Requires-Dist: uv>=0.1.0; extra == 'all'
Provides-Extra: dev
Requires-Dist: black>=23.10.1; extra == 'dev'
Requires-Dist: flake8>=6.1.0; extra == 'dev'
Requires-Dist: isort>=5.12.0; extra == 'dev'
Requires-Dist: mypy>=1.6.1; extra == 'dev'
Requires-Dist: pre-commit>=3.5.0; extra == 'dev'
Requires-Dist: pytest-cov>=4.1.0; extra == 'dev'
Requires-Dist: pytest-mock>=3.12.0; extra == 'dev'
Requires-Dist: pytest-playwright-asyncio>=0.7.0; extra == 'dev'
Requires-Dist: pytest-playwright>=0.7.0; extra == 'dev'
Requires-Dist: pytest-sugar>=0.9.7; extra == 'dev'
Requires-Dist: pytest>=7.4.3; extra == 'dev'
Requires-Dist: ruff>=0.0.260; extra == 'dev'
Requires-Dist: tox>=4.11.3; extra == 'dev'
Requires-Dist: uv>=0.1.0; extra == 'dev'
